odoo10_addon_sale_procurement_analytic-10.0.1.0.0-py2.7-nspkg.pth
odoo/addons/sale_procurement_analytic/README.rst
odoo/addons/sale_procurement_analytic/__init__.py
odoo/addons/sale_procurement_analytic/__manifest__.py
odoo/addons/sale_procurement_analytic/models/__init__.py
odoo/addons/sale_procurement_analytic/models/product.py
odoo/addons/sale_procurement_analytic/models/sale.py
odoo/addons/sale_procurement_analytic/static/description/icon.png
odoo/addons/sale_procurement_analytic/tests/__init__.py
odoo/addons/sale_procurement_analytic/tests/test_sale_procurement_analytic.py
odoo10_addon_sale_procurement_analytic-10.0.1.0.0.dist-info/DESCRIPTION.rst
odoo10_addon_sale_procurement_analytic-10.0.1.0.0.dist-info/METADATA
odoo10_addon_sale_procurement_analytic-10.0.1.0.0.dist-info/RECORD
odoo10_addon_sale_procurement_analytic-10.0.1.0.0.dist-info/WHEEL
odoo10_addon_sale_procurement_analytic-10.0.1.0.0.dist-info/metadata.json
odoo10_addon_sale_procurement_analytic-10.0.1.0.0.dist-info/namespace_packages.txt
odoo10_addon_sale_procurement_analytic-10.0.1.0.0.dist-info/top_level.txt
